{
    "id": 0,
    "nombreParticipante": "",
    "mainImg": "",
    "ubicacion": {
        "Region": "",
        "Comuna": "",
        "Territorio": "",
        "Pais": ""
    },
    "categoria": [
        {
            "nombre": "Amor",
            "imgObjeto": "link",
            "videoObjeto": "link",
            "cita1": "texto",
            "cita2": "texto"
        },
        {
            "nombre": "Miedo",
            "imgObjeto": "link",
            "videoObjeto": "link",
            "cita1": "texto",
            "cita2": "texto"
        },
        {
            "nombre": "Familia",
            "imgObjeto": "link",
            "videoObjeto": "link",
            "cita1": "texto",
            "cita2": "texto"
        },
        {
            "nombre": "Cuerpo",
            "imgObjeto": "link",
            "videoObjeto": "link",
            "cita1": "texto",
            "cita2": "texto"
        },
        {
            "nombre": "Libertad",
            "imgObjeto": "link",
            "videoObjeto": "link",
            "cita1": "texto",
            "cita2": "texto"
        },
        {
            "nombre": "Actosentido",
            "imgObjeto": "link",
            "videoObjeto": "link",
            "cita1": "texto",
            "cita2": "texto"
        }
    ]
}